qc_firmware/Verilog_Modules/1_to_8/demux.v
module demux_1_8(
		 input [2:0] sel,
		 input	    i,
		 input      clk,
		 output reg y0, y1, y2, y3, y4, y5, y6, y7);

   always @(posedge clk) begin
      case(sel)
	3'h0: {y0,y1,y2,y3,y4,y5,y6,y7} = {i, 1'b0, 1'b0, 1'b0, 1'b0, 1'b0, 1'b0, 1'b0};
	3'h1: {y0,y1,y2,y3,y4,y5,y6,y7} = {1'b0, i, 1'b0, 1'b0, 1'b0, 1'b0, 1'b0, 1'b0};
	3'h2: {y0,y1,y2,y3,y4,y5,y6,y7} = {1'b0, 1'b0, i, 1'b0, 1'b0, 1'b0, 1'b0, 1'b0};
	3'h3: {y0,y1,y2,y3,y4,y5,y6,y7} = {1'b0, 1'b0, 1'b0, i, 1'b0, 1'b0, 1'b0, 1'b0};
	3'h4: {y0,y1,y2,y3,y4,y5,y6,y7} = {1'b0, 1'b0, 1'b0, 1'b0, i, 1'b0, 1'b0, 1'b0};
	3'h5: {y0,y1,y2,y3,y4,y5,y6,y7} = {1'b0, 1'b0, 1'b0, 1'b0, 1'b0, i, 1'b0, 1'b0};
	3'h6: {y0,y1,y2,y3,y4,y5,y6,y7} = 8'h0;
	3'h7: {y0,y1,y2,y3,y4,y5,y6,y7} = 8'h0;
	
      endcase // case (sel)
   end // always @ (*)
endmodule

Verilog_Modules/1_to_8/demux_tb.v
`include "demux.v"
`timescale 1ns / 1ps

module demux_tb(
);
 	reg [2:0] sel;
	reg i;
	reg clk;
	wire y0, y1, y2, y3, y4, y5, y6;
	
	parameter HALF_CYCLE = 50;
	parameter CYCLE = 100;
	parameter PAUSE = 5 * CYCLE;

	demux_1_8 demux_inst(
		.sel(sel),
		.i(i),
		.clk(clk),
		.y0(y0),
		.y1(y1),
		.y2(y2),
		.y3(y3),
		.y4(y4),
		.y5(y5),
		.y6(y6)
	);

	always
		begin
			forever #HALF_CYCLE clk = !clk;
		end
	
	initial begin
		$dumpfile("demux.vcd");
		$dumpvars(0, sel, i, clk, y0, y1, y2, y3, y4, y5, y6);
		clk = 1'b0;
		i = 1'b1;
		#PAUSE

		sel = 3'h0;
		#PAUSE;

		sel = 3'h1;
		#PAUSE;

		sel = 3'h2;
		#PAUSE;

		sel = 3'h3;
		#PAUSE;

		sel = 3'h4;
		#PAUSE;

		sel = 3'h5;
		#PAUSE;

		sel = 3'h6;
		#PAUSE;
		$finish;

	end
endmodule

qc_firmware/Verilog_Modules/1_to_8/demux.vcd
$date
	Tue Aug  5 12:00:17 2025
$end
$version
	Icarus Verilog
$end
$timescale
	1ps
$end
$scope module demux_tb $end
$var reg 3 ! sel [2:0] $end
$upscope $end
$scope module demux_tb $end
$var reg 1 " i $end
$upscope $end
$scope module demux_tb $end
$var reg 1 # clk $end
$upscope $end
$scope module demux_tb $end
$var wire 1 $ y0 $end
$upscope $end
$scope module demux_tb $end
$var wire 1 % y1 $end
$upscope $end
$scope module demux_tb $end
$var wire 1 & y2 $end
$upscope $end
$scope module demux_tb $end
$var wire 1 ' y3 $end
$upscope $end
$scope module demux_tb $end
$var wire 1 ( y4 $end
$upscope $end
$scope module demux_tb $end
$var wire 1 ) y5 $end
$upscope $end
$scope module demux_tb $end
$var wire 1 * y6 $end
$upscope $end
$enddefinitions $end
#0
$dumpvars
x*
x)
x(
x'
x&
x%
x$
0#
1"
bx !
$end
#50000
1#
#100000
0#
#150000
1#
#200000
0#
#250000
1#
#300000
0#
#350000
1#
#400000
0#
#450000
1#
#500000
0#
b0 !
#550000
1$
0%
0&
0'
0(
0)
0*
1#
#600000
0#
#650000
1#
#700000
0#
#750000
1#
#800000
0#
#850000
1#
#900000
0#
#950000
1#
#1000000
0#
b1 !
#1050000
0$
1%
1#
#1100000
0#
#1150000
1#
#1200000
0#
#1250000
1#
#1300000
0#
#1350000
1#
#1400000
0#
#1450000
1#
#1500000
0#
b10 !
#1550000
0%
1&
1#
#1600000
0#
#1650000
1#
#1700000
0#
#1750000
1#
#1800000
0#
#1850000
1#
#1900000
0#
#1950000
1#
#2000000
0#
b11 !
#2050000
0&
1'
1#
#2100000
0#
#2150000
1#
#2200000
0#
#2250000
1#
#2300000
0#
#2350000
1#
#2400000
0#
#2450000
1#
#2500000
0#
b100 !
#2550000
0'
1(
1#
#2600000
0#
#2650000
1#
#2700000
0#
#2750000
1#
#2800000
0#
#2850000
1#
#2900000
0#
#2950000
1#
#3000000
0#
b101 !
#3050000
0(
1)
1#
#3100000
0#
#3150000
1#
#3200000
0#
#3250000
1#
#3300000
0#
#3350000
1#
#3400000
0#
#3450000
1#
#3500000
0#
b110 !
#3550000
0)
1#
